xmlplot/__init__.py
xmlplot/common.py
xmlplot/errortrap.py
xmlplot/expressions.py
xmlplot/functions.py
xmlplot/georef.py
xmlplot/gui_qt4.py
xmlplot/mpl_backend_qt4.py
xmlplot/plot.py
xmlplot/xmlplot-1.0.xsd
xmlplot/data/__init__.py
xmlplot/data/gotmtext.py
xmlplot/data/hdf4.py
xmlplot/data/netcdf.py
xmlplot/icons/agt_multimedia.png
xmlplot/icons/camera.png
xmlplot/icons/configure.png
xmlplot/icons/delete_table_row.png
xmlplot/icons/exit.png
xmlplot/icons/fileopen.png
xmlplot/icons/fileprint.png
xmlplot/icons/filesaveas.png
xmlplot/icons/funct.png
xmlplot/icons/insert_table_row.png
xmlplot/icons/new_window.png
xmlplot/icons/player_end1.png
xmlplot/icons/player_pause.png
xmlplot/icons/player_play.png
xmlplot/icons/player_start.png
xmlplot/icons/readme.txt
xmlplot/icons/viewmag.png
xmlplot/icons/viewmagfit.png
xmlplot/schemas/datafilecache/0001.schema
xmlplot/schemas/figure/0001.schema
xmlplot/schemas/figure/0002.schema
xmlplot/schemas/figure/0002_0003.converter
xmlplot/schemas/figure/0003.schema
xmlplot-0.9.32.dist-info/METADATA
xmlplot-0.9.32.dist-info/WHEEL
xmlplot-0.9.32.dist-info/licenses/LICENSE
xmlplot-0.9.32.dist-info/RECORD
